mytot/__init__.py
mytot/config.py
mytot/kill_demo.py
mytot/main.py
mytot/send_email.py
mytot/test_task.py
mytot-2025.12.4.data/data/LICENSE
mytot-2025.12.4.dist-info/LICENSE
mytot-2025.12.4.dist-info/METADATA
mytot-2025.12.4.dist-info/WHEEL
mytot-2025.12.4.dist-info/entry_points.txt
mytot-2025.12.4.dist-info/top_level.txt
mytot-2025.12.4.dist-info/RECORD
