Metadata-Version: 2.1
Name: mytot
Version: 2025.12.4
Summary: Tool of Tool
Author: Xin-Xin MA
License: GPL
License-File: LICENSE
Requires-Dist: loguru
Requires-Dist: psutil
Requires-Dist: yagmail
